converterpro/__init__.py
converterpro/weight_converter.py
converterpro-0.1.2.dist-info/LICENSE
converterpro-0.1.2.dist-info/WHEEL
converterpro-0.1.2.dist-info/METADATA
converterpro-0.1.2.dist-info/RECORD
