Metadata-Version: 2.1
Name: converterpro
Version: 0.1.2
Summary: Python converter library
Home-page: http://converterpro.readthedocs.io/
License: Apache-2.0
Keywords: weight-conversion,converter,oforiwaasam
Author: Lily Sam
Author-email: los2119@columbia.edu
Requires-Python: >=3.9,<4.0
Classifier: Development Status :: 3 - Alpha
Classifier: License :: OSI Approved :: Apache Software License
Classifier: Programming Language :: Python :: 3
Classifier: Programming Language :: Python :: 3.9
Classifier: Programming Language :: Python :: 3.10
Classifier: Programming Language :: Python :: 3.11
Classifier: Programming Language :: Python :: 3
Classifier: Programming Language :: Python :: 3.10
Classifier: Programming Language :: Python :: 3.11
Classifier: Programming Language :: Python :: 3.7
Classifier: Programming Language :: Python :: 3.8
Classifier: Programming Language :: Python :: 3.9
Classifier: Programming Language :: Python :: Implementation :: CPython
Classifier: Programming Language :: Python :: Implementation :: PyPy
Project-URL: Repository, https://github.com/oforiwaasam/converterpro
